.clang-format
.flake8
.gitignore
.gitmodules
CHANGELOG.md
CODEOWNERS
CODE_OF_CONDUCT
Dockerfile
Dockerfile-cuda
Dockerfile-embedded
LICENSE
MANIFEST.in
Makefile
README.md
__init__.py
description.txt
packages.txt
setup.py
./src/opendr/__init__.py
./src/opendr/_setup.py
./src/opendr/_version.py
./src/opendr/control/__init__.py
./src/opendr/engine/__init__.py
./src/opendr/engine/constants.py
./src/opendr/engine/data.py
./src/opendr/engine/datasets.py
./src/opendr/engine/example_learner.py
./src/opendr/engine/learners.py
./src/opendr/engine/target.py
./src/opendr/perception/__init__.py
./src/opendr/perception/speech_recognition/__init__.py
./src/opendr/perception/speech_recognition/edgespeechnets/README.md
./src/opendr/perception/speech_recognition/edgespeechnets/__init__.py
./src/opendr/perception/speech_recognition/edgespeechnets/dependencies.ini
./src/opendr/perception/speech_recognition/edgespeechnets/edgespeechnets_learner.py
./src/opendr/perception/speech_recognition/edgespeechnets/algorithm/__init__.py
./src/opendr/perception/speech_recognition/edgespeechnets/algorithm/audioutils.py
./src/opendr/perception/speech_recognition/edgespeechnets/algorithm/models.py
./src/opendr/perception/speech_recognition/matchboxnet/README.md
./src/opendr/perception/speech_recognition/matchboxnet/__init__.py
./src/opendr/perception/speech_recognition/matchboxnet/dependencies.ini
./src/opendr/perception/speech_recognition/matchboxnet/matchboxnet_learner.py
./src/opendr/perception/speech_recognition/matchboxnet/algorithm/__init__.py
./src/opendr/perception/speech_recognition/matchboxnet/algorithm/audioutils.py
./src/opendr/perception/speech_recognition/matchboxnet/algorithm/model.py
./src/opendr/perception/speech_recognition/quadraticselfonn/README.md
./src/opendr/perception/speech_recognition/quadraticselfonn/__init__.py
./src/opendr/perception/speech_recognition/quadraticselfonn/dependencies.ini
./src/opendr/perception/speech_recognition/quadraticselfonn/quadraticselfonn_learner.py
./src/opendr_toolkit_speech_recognition.egg-info/PKG-INFO
./src/opendr_toolkit_speech_recognition.egg-info/SOURCES.txt
./src/opendr_toolkit_speech_recognition.egg-info/dependency_links.txt
./src/opendr_toolkit_speech_recognition.egg-info/requires.txt
./src/opendr_toolkit_speech_recognition.egg-info/top_level.txt
